pyecwid/__init__.py
pyecwid/ecwidapi.py
pyecwid/ecwidapi_mock.py
pyecwid/ecwidutils.py
pyecwid/endpoints/__init__.py
pyecwid/endpoints/coupons.py
pyecwid/endpoints/customers.py
pyecwid/endpoints/endpoint.py
pyecwid/endpoints/orders.py
pyecwid/endpoints/products.py
pyecwid/endpoints/producttypes.py
pyecwid/endpoints/mixins/__init__.py
pyecwid/endpoints/mixins/add.py
pyecwid/endpoints/mixins/delete.py
pyecwid/endpoints/mixins/get_all.py
pyecwid/endpoints/mixins/get_by_id.py
pyecwid/endpoints/mixins/get_by_keyword.py
pyecwid/endpoints/mixins/get_by_params.py
pyecwid/endpoints/mixins/update.py
pyecwid/validators/__init__.py
pyecwid/validators/paramater_validators.py
tests/__init__.py
tests/test_ecwid_endpoint_coupons.py
tests/test_ecwid_endpoint_customers.py
tests/test_ecwid_endpoint_products.py
tests/test_ecwid_endpoint_producttypes.py
tests/test_ecwidapi.py
pyecwid-0.1.1.dist-info/LICENSE
pyecwid-0.1.1.dist-info/METADATA
pyecwid-0.1.1.dist-info/WHEEL
pyecwid-0.1.1.dist-info/top_level.txt
pyecwid-0.1.1.dist-info/RECORD
