Metadata-Version: 2.1
Name: pyecwid
Version: 0.1.1
Summary: An interface to the Ecwid shopping platform API
Home-page: https://github.com/DanPalmz/pyecwid
Author: Dan Palmer
Author-email: ecwid@danpalmz.com
License: UNKNOWN
Platform: UNKNOWN
Classifier: Programming Language :: Python :: 3
Classifier: License :: OSI Approved :: MIT License
Classifier: Operating System :: OS Independent
Requires-Python: >=3.6
Requires-Dist: requests
Provides-Extra: test
Requires-Dist: pytest ; extra == 'test'
Requires-Dist: pytest-dependency ; extra == 'test'
Requires-Dist: pytest-dotenv ; extra == 'test'
